LICENSE
MANIFEST.in
README.md
setup.py
currencies/__init__.py
currencies/admin.py
currencies/conf.py
currencies/managers.py
currencies/middleware.py
currencies/models.py
currencies/urls.py
currencies/utils.py
currencies/views.py
currencies/locale/el/LC_MESSAGES/django.mo
currencies/locale/el/LC_MESSAGES/django.po
currencies/locale/es/LC_MESSAGES/django.mo
currencies/locale/es/LC_MESSAGES/django.po
currencies/locale/ru/LC_MESSAGES/django.mo
currencies/locale/ru/LC_MESSAGES/django.po
currencies/management/__init__.py
currencies/management/commands/__init__.py
currencies/management/commands/currencies.json
currencies/management/commands/currencies.py
currencies/management/commands/update_rates.py
currencies/migrations/0001_initial.py
currencies/migrations/__init__.py
currencies/templatetags/__init__.py
currencies/templatetags/currencies.py
django_simple_currencies.egg-info/PKG-INFO
django_simple_currencies.egg-info/SOURCES.txt
django_simple_currencies.egg-info/dependency_links.txt
django_simple_currencies.egg-info/requires.txt
django_simple_currencies.egg-info/top_level.txt