Metadata-Version: 1.1
Name: django-simple-currencies
Version: 0.1
Summary: Currency, exchange rate and conversions support for django projects
Home-page: https://github.com/bashu/django-simple-currencies
Author: Basil Shubin
Author-email: basil.shubin@gmail.com
License: BSD License
Platform: UNKNOWN
Classifier: Environment :: Web Environment
Classifier: Framework :: Django
Classifier: Intended Audience :: Developers
Classifier: License :: OSI Approved :: BSD License
Classifier: Operating System :: OS Independent
Classifier: Programming Language :: Python
Classifier: Topic :: Internet :: WWW/HTTP
Classifier: Topic :: Internet :: WWW/HTTP :: Dynamic Content
